{
  "total_prompts": 39,
  "total_authors": 16,
  "total_tags": 51,
  "tag_frequency": {
    "抽象": 5,
    "vtuber": 1,
    "粘人": 1,
    "亚托莉": 1,
    "女高中生": 1,
    "AstrBot": 1,
    "Roleplay": 1,
    "奇怪的知识又增加了": 1,
    "孙笑川": 1,
    "幽默": 1,
    "原神": 1,
    "赞妮": 1,
    "猫娘": 5,
    "小男娘": 1,
    "自信": 2,
    "哲学": 1,
    "穿越": 1,
    "水星领航员": 1,
    "伪人": 2,
    "命运石之门": 1,
    "赛博女友": 1,
    "虚拟主播": 2,
    "娱乐游戏": 2,
    "性转": 1,
    "我超爱学数学": 1,
    "民科": 1,
    "YJ": 1,
    "通用": 4,
    "嘴臭": 1,
    "可爱": 5,
    "技术狂": 1,
    "元气": 1,
    "锐锐": 1,
    "小学生": 1,
    "治愈": 1,
    "贴吧": 1,
    "傲娇": 2,
    "钟离": 1,
    "八卦": 1,
    "拟人": 1,
    "水无灯里": 1,
    "鸣潮": 2,
    "雌小鬼": 1,
    "反差": 1,
    "上班族": 1,
    "今汐": 1,
    "妹妹": 1,
    "Galgame": 2,
    "ARIA": 1,
    "温柔": 2,
    "安全": 1
  },
  "last_updated": 1749543867.719901
}